{"ongoing_trials": {"tuner0": "0001"}, "hyperparameters": {"space": [{"class_name": "Int", "config": {"name": "units", "default": null, "conditions": [], "min_value": 16, "max_value": 128, "step": 16, "sampling": null}}], "values": {"units": 16}}, "seed": 6279, "seed_state": 6281, "tried_so_far": ["6c6c7588a891dfd2b3a98d59252c7f19", "709168175c198aa0cdda0e6fe7f7354e"], "hyperband_iterations": 1, "max_epochs": 10, "min_epochs": 1, "factor": 3, "brackets": [{"bracket_num": 2, "rounds": [[{"past_id": null, "id": "0000"}, {"past_id": null, "id": "0001"}], [], []]}], "current_bracket": 2, "current_iteration": 0}